math_tompy/__init__.py
math_tompy/decimal.py
math_tompy/exceptions.py
math_tompy/float.py
math_tompy/inequality.py
math_tompy/integer.py
math_tompy/special.py
math_tompy/symbolic.py
math_tompy/symbolic_point2d.py
math_tompy-2025.10.10.18.2.dist-info/METADATA
math_tompy-2025.10.10.18.2.dist-info/WHEEL
math_tompy-2025.10.10.18.2.dist-info/RECORD
