Metadata-Version: 2.4
Name: math-tompy
Version: 2025.10.10.18.2
Summary: Extra math for tompy projects
Author: tompy
Classifier: Development Status :: 3 - Alpha
Classifier: Intended Audience :: Developers
Classifier: License :: OSI Approved :: GNU General Public License v3 (GPLv3)
Classifier: Operating System :: OS Independent
Classifier: Programming Language :: Python :: 3.9
Requires-Python: >=3.9
Requires-Dist: angle-tompy>=2025.5.5.11.2
Requires-Dist: sympy>=1.14.0
